skosmos_client.py
skosmos_client-0.3.0.dist-info/LICENSE.txt
skosmos_client-0.3.0.dist-info/METADATA
skosmos_client-0.3.0.dist-info/WHEEL
skosmos_client-0.3.0.dist-info/top_level.txt
skosmos_client-0.3.0.dist-info/RECORD
