Metadata-Version: 2.1
Name: skosmos-client
Version: 0.3.0
Summary: Python client library for accessing Skosmos REST API
Home-page: https://github.com/NatLibFi/Skosmos-client
Author: Osma Suominen
Author-email: osma.suominen@helsinki.fi
License: UNKNOWN
Platform: UNKNOWN
Classifier: Programming Language :: Python :: 3
Classifier: License :: OSI Approved :: Apache Software License
Classifier: Operating System :: OS Independent
Requires-Dist: requests
Requires-Dist: rdflib
Provides-Extra: dev
Requires-Dist: bumpversion ; extra == 'dev'
